{"expireTime":9007200876971668000,"key":"51ed9eb85f89dc2aefd2abc6ccb31dbc","val":{"name":"IMAGE_PROCESSING","inputPaths":["/Users/eddy/Documents/profile/src/pages/artworks/crossv2/img0.jpg"],"outputDir":"/Users/eddy/Documents/profile/public/static/996771c373d70acee6f13c4ee2414789","args":{"isLazy":false,"operations":[{"outputPath":"61e93/img0.webp","args":{"width":200,"cropFocus":17,"toFormat":"webp","fit":"cover","background":"rgba(0,0,0,1)"}},{"outputPath":"1f5c5/img0.webp","args":{"width":400,"cropFocus":17,"toFormat":"webp","fit":"cover","background":"rgba(0,0,0,1)"}},{"outputPath":"58556/img0.webp","args":{"width":800,"cropFocus":17,"toFormat":"webp","fit":"cover","background":"rgba(0,0,0,1)"}},{"outputPath":"99238/img0.webp","args":{"width":1200,"cropFocus":17,"toFormat":"webp","fit":"cover","background":"rgba(0,0,0,1)"}},{"outputPath":"7c22d/img0.webp","args":{"width":1600,"cropFocus":17,"toFormat":"webp","fit":"cover","background":"rgba(0,0,0,1)"}},{"outputPath":"4fb18/img0.webp","args":{"width":2880,"cropFocus":17,"toFormat":"webp","fit":"cover","background":"rgba(0,0,0,1)"}}],"pluginOptions":{"base64Width":20,"forceBase64Format":"","useMozJpeg":false,"stripMetadata":true,"lazyImageGeneration":true,"defaultQuality":50,"failOnError":true,"plugins":[]}}}}